snowddl/__init__.py
snowddl/config.py
snowddl/context.py
snowddl/engine.py
snowddl/error.py
snowddl/formatter.py
snowddl/model.py
snowddl/query_builder.py
snowddl/settings.py
snowddl/version.py
snowddl/_config/sample01_01/business_role.yaml
snowddl/_config/sample01_01/technical_role.yaml
snowddl/_config/sample01_01/user.yaml
snowddl/_config/sample01_01/warehouse.yaml
snowddl/_config/sample01_01/snowddl_db/bookings/params.yaml
snowddl/_config/sample01_01/snowddl_db/bookings/function/lang(object).yaml
snowddl/_config/sample01_01/snowddl_db/bookings/function/now().yaml
"snowddl/_config/sample01_01/snowddl_db/bookings/procedure/check_in(varchar,number,number,varchar).yaml"
snowddl/_config/sample01_01/snowddl_db/bookings/sequence/flights_id_seq.yaml
snowddl/_config/sample01_01/snowddl_db/bookings/table/aircrafts_data.yaml
snowddl/_config/sample01_01/snowddl_db/bookings/table/airports_data.yaml
snowddl/_config/sample01_01/snowddl_db/bookings/table/boarding_passes.yaml
snowddl/_config/sample01_01/snowddl_db/bookings/table/bookings.yaml
snowddl/_config/sample01_01/snowddl_db/bookings/table/flights.yaml
snowddl/_config/sample01_01/snowddl_db/bookings/table/seats.yaml
snowddl/_config/sample01_01/snowddl_db/bookings/table/ticket_flights.yaml
snowddl/_config/sample01_01/snowddl_db/bookings/table/tickets.yaml
snowddl/_config/sample01_01/snowddl_db/bookings/view/aircrafts.yaml
snowddl/_config/sample01_01/snowddl_db/bookings/view/airports.yaml
snowddl/_config/sample01_01/snowddl_db/bookings/view/flights_v.yaml
snowddl/_config/sample01_01/snowddl_db/bookings/view/routes.yaml
snowddl/_config/sample01_01/snowddl_db/sakila/table/actor.yaml
snowddl/_config/sample01_01/snowddl_db/sakila/table/address.yaml
snowddl/_config/sample01_01/snowddl_db/sakila/table/category.yaml
snowddl/_config/sample01_01/snowddl_db/sakila/table/city.yaml
snowddl/_config/sample01_01/snowddl_db/sakila/table/country.yaml
snowddl/_config/sample01_01/snowddl_db/sakila/table/customer.yaml
snowddl-0.62.0.dist-info/licenses/LICENSE.txt
snowddl-0.62.0.dist-info/METADATA
snowddl-0.62.0.dist-info/WHEEL
snowddl-0.62.0.dist-info/entry_points.txt
snowddl-0.62.0.dist-info/top_level.txt
snowddl-0.62.0.dist-info/RECORD
