Metadata-Version: 2.4
Name: snowddl
Version: 0.62.0
Summary: Object management automation tool for Snowflake
Author-email: Vitaly Markov <wild.desu@gmail.com>
License-Expression: MIT AND (Apache-2.0 OR BSD-2-Clause)
Project-URL: Homepage, https://github.com/littleK0i/snowddl
Keywords: snowflake,database,schema,object,change,ddl,sql,create,alter,drop,grant,table,view
Classifier: Development Status :: 4 - Beta
Classifier: Operating System :: OS Independent
Classifier: Intended Audience :: Developers
Classifier: Topic :: Database
Classifier: Programming Language :: Python :: 3.9
Classifier: Programming Language :: Python :: 3.10
Classifier: Programming Language :: Python :: 3.11
Classifier: Programming Language :: Python :: 3.12
Classifier: Programming Language :: Python :: 3.13
Requires-Python: >=3.9
License-File: LICENSE.txt
Requires-Dist: jsonschema~=4.18
Requires-Dist: pydantic~=2.4
Requires-Dist: pyyaml~=6.0
Requires-Dist: snowflake-connector-python~=3.0
Provides-Extra: convert
Requires-Dist: sqlglot; extra == "convert"
Provides-Extra: dev
Requires-Dist: black; extra == "dev"
Requires-Dist: pytest; extra == "dev"
Requires-Dist: ruff; extra == "dev"
Provides-Extra: sso-caching
Requires-Dist: snowflake-connector-python[secure-local-storage]~=3.0; extra == "sso-caching"
Dynamic: license-file
